{
  "title": "New",
  "description": "New",
  "pages": [
    {
      "name": "Name",
      "elements": [
        {
          "type": "text",
          "name": "FirstName",
          "title": "Enter your first name:",
          "isRequired": true
        },
        {
          "type": "comment",
          "name": "LastName",
          "title": "Enter your last name:",
          "isRequired": true
        },
        {
          "type": "radiogroup",
          "name": "question1",
          "title": "Select",
          "choices": ["Item 1", "Item 2", "Item 3"]
        },
        {
          "type": "boolean",
          "name": "question2"
        }
      ],
      "title": "page 1",
      "description": "page 1"
    },
    {
      "name": "page1",
      "elements": [
        {
          "type": "rating",
          "name": "question3"
        },
        {
          "type": "checkbox",
          "name": "question4",
          "choices": ["Item 1", "Item 2", "Item 3"]
        }
      ],
      "title": "Page 2",
      "description": "nsana"
    },
    {
      "name": "page2",
      "elements": [
        {
          "type": "dropdown",
          "name": "question5",
          "choices": ["Item 1", "Item 2", "Item 3"]
        },
        {
          "type": "tagbox",
          "name": "question6",
          "choices": ["Item 1", "Item 2", "Item 3"]
        },
        {
          "type": "file",
          "name": "question7"
        },
        {
          "type": "imagepicker",
          "name": "question8",
          "choices": [
            {
              "value": "Image 1",
              "imageLink": "https://surveyjs.io/Content/Images/examples/image-picker/lion.jpg"
            },
            {
              "value": "Image 2",
              "imageLink": "https://surveyjs.io/Content/Images/examples/image-picker/giraffe.jpg"
            },
            {
              "value": "Image 3",
              "imageLink": "https://surveyjs.io/Content/Images/examples/image-picker/panda.jpg"
            },
            {
              "value": "Image 4",
              "imageLink": "https://surveyjs.io/Content/Images/examples/image-picker/camel.jpg"
            }
          ],
          "imageFit": "cover"
        },
        {
          "type": "ranking",
          "name": "question9",
          "choices": ["Item 1", "Item 2", "Item 3"]
        },
        {
          "type": "html",
          "name": "question10"
        },
        {
          "type": "signaturepad",
          "name": "question11"
        }
      ],
      "title": "page 3",
      "description": "page 3"
    }
  ]
}



{
  "FirstName": "krishanrtha",
  "LastName": "krishantha",
  "question1": [
      "Item 1",
      "Item 3"
  ],
  "question2": [
      "Item 2",
      "Item 3"
  ],
  "question3": "sdad"
}